[
  {
    "id": 88,
    "date": "2026-04-22",
    "model": "k_props",
    "game": "Philadelphia Phillies @ Chicago Cubs",
    "play": "Kyle Backhus Over 1.1 Ks",
    "edge_pct": 21.4,
    "our_prob": 1.3,
    "market_prob": 1.1,
    "best_odds": -105,
    "best_book": "Pinnacle",
    "key_features": {
      "k_per_9": 12.2,
      "opp_k_rate": 0.212,
      "recent_k_avg": 1.6
    },
    "result": "NO_ACTION",
    "actual_score": "pitcher stats not found",
    "created_at": "2026-04-22T10:30:28.310140",
    "settled_at": "2026-04-23T09:00:06.246865"
  },
  {
    "id": 87,
    "date": "2026-04-22",
    "model": "f5_under",
    "game": "Milwaukee Brewers @ Detroit Tigers",
    "play": "F5 Under 5.6",
    "edge_pct": 47.7,
    "our_prob": 77.3,
    "market_prob": 52.4,
    "best_odds": 102,
    "best_book": "FanDuel",
    "key_features": {
      "away_pitcher_era_l5": 1.18,
      "home_pitcher_era_l5": 3.36,
      "park_factor": 0.96
    },
    "result": "W",
    "actual_score": "1-4",
    "created_at": "2026-04-22T10:30:28.306885",
    "settled_at": "2026-04-23T09:00:06.243944"
  },
  {
    "id": 86,
    "date": "2026-04-22",
    "model": "f5_under",
    "game": "Chicago White Sox @ Arizona Diamondbacks",
    "play": "F5 Under 5.0",
    "edge_pct": 47.9,
    "our_prob": 77.5,
    "market_prob": 52.4,
    "best_odds": 105,
    "best_book": "Pinnacle",
    "key_features": {
      "away_pitcher_era_l5": 3.23,
      "home_pitcher_era_l5": 0.61,
      "park_factor": 1.0
    },
    "result": "L",
    "actual_score": "4-8",
    "created_at": "2026-04-22T10:30:28.302387",
    "settled_at": "2026-04-23T09:00:06.240437"
  },
  {
    "id": 85,
    "date": "2026-04-22",
    "model": "ip_props",
    "game": "Baltimore Orioles @ Kansas City Royals",
    "play": "Michael Wacha Over 17.5 Outs",
    "edge_pct": 48.6,
    "our_prob": 26.0,
    "market_prob": 17.5,
    "best_odds": 100,
    "best_book": "BetMGM",
    "key_features": {
      "avg_ip_last_5": 6.8,
      "opp_k_rate": 0.25
    },
    "result": "NO_ACTION",
    "actual_score": "pitcher stats not found",
    "created_at": "2026-04-22T10:30:28.299695",
    "settled_at": "2026-04-23T09:00:06.237037"
  },
  {
    "id": 84,
    "date": "2026-04-22",
    "model": "ip_props",
    "game": "Philadelphia Phillies @ Chicago Cubs",
    "play": "Kyle Backhus Under 17.5 Outs",
    "edge_pct": 54.3,
    "our_prob": 8.0,
    "market_prob": 17.5,
    "best_odds": -105,
    "best_book": "Pinnacle",
    "key_features": {
      "avg_ip_last_3": 0.8,
      "days_rest": 2
    },
    "result": "NO_ACTION",
    "actual_score": "pitcher stats not found",
    "created_at": "2026-04-22T10:30:28.295218",
    "settled_at": "2026-04-23T09:00:06.248253"
  },
  {
    "id": 83,
    "date": "2026-04-21",
    "model": "ip_props",
    "game": "Athletics @ Seattle Mariners",
    "play": "Luis Castillo Under 17.5 Outs",
    "edge_pct": 25.7,
    "our_prob": 13.0,
    "market_prob": 17.5,
    "best_odds": 103,
    "best_book": "Pinnacle",
    "key_features": {
      "avg_ip_last_3": 3.8,
      "days_rest": 5
    },
    "result": "NO_ACTION",
    "actual_score": "pitcher stats not found",
    "created_at": "2026-04-21T10:30:26.194958",
    "settled_at": "2026-04-22T09:00:03.488147"
  },
  {
    "id": 82,
    "date": "2026-04-21",
    "model": "f5_under",
    "game": "Milwaukee Brewers @ Detroit Tigers",
    "play": "F5 Under 5.4",
    "edge_pct": 33.2,
    "our_prob": 69.8,
    "market_prob": 52.4,
    "best_odds": -107,
    "best_book": "Pinnacle",
    "key_features": {
      "away_pitcher_era_l5": 2.49,
      "home_pitcher_era_l5": 3.07,
      "park_factor": 0.96
    },
    "result": "W",
    "actual_score": "3-1",
    "created_at": "2026-04-21T10:30:26.192101",
    "settled_at": "2026-04-22T09:00:03.497506"
  },
  {
    "id": 81,
    "date": "2026-04-21",
    "model": "f5_under",
    "game": "Atlanta Braves @ Washington Nationals",
    "play": "F5 Under 6.5",
    "edge_pct": 42.6,
    "our_prob": 74.7,
    "market_prob": 52.4,
    "best_odds": -102,
    "best_book": "Pinnacle",
    "key_features": {
      "away_pitcher_era_l5": 1.62,
      "home_pitcher_era_l5": 2.78,
      "park_factor": 1.0
    },
    "result": "L",
    "actual_score": "3-5",
    "created_at": "2026-04-21T10:30:26.188656",
    "settled_at": "2026-04-22T09:00:03.491035"
  },
  {
    "id": 80,
    "date": "2026-04-21",
    "model": "f5_under",
    "game": "Los Angeles Dodgers @ San Francisco Giants",
    "play": "F5 Under 5.5",
    "edge_pct": 44.0,
    "our_prob": 75.4,
    "market_prob": 52.4,
    "best_odds": 100,
    "best_book": "DraftKings",
    "key_features": {
      "away_pitcher_era_l5": 2.65,
      "home_pitcher_era_l5": 2.46,
      "park_factor": 0.95
    },
    "result": "W",
    "actual_score": "1-3",
    "created_at": "2026-04-21T10:30:26.183792",
    "settled_at": "2026-04-22T09:00:03.494635"
  },
  {
    "id": 79,
    "date": "2026-04-20",
    "model": "ip_props",
    "game": "Toronto Blue Jays @ Los Angeles Angels",
    "play": "Dylan Cease Under 17.5 Outs",
    "edge_pct": 14.3,
    "our_prob": 15.0,
    "market_prob": 17.5,
    "best_odds": -101,
    "best_book": "Pinnacle",
    "key_features": {
      "avg_ip_last_3": 5.0,
      "days_rest": 5
    },
    "result": "NO_ACTION",
    "actual_score": "pitcher stats not found",
    "created_at": "2026-04-20T10:30:19.786118",
    "settled_at": "2026-04-21T09:00:06.176683"
  },
  {
    "id": 78,
    "date": "2026-04-20",
    "model": "ip_props",
    "game": "Detroit Tigers @ Boston Red Sox",
    "play": "Jack Flaherty Under 17.5 Outs",
    "edge_pct": 14.3,
    "our_prob": 15.0,
    "market_prob": 17.5,
    "best_odds": -102,
    "best_book": "BetMGM",
    "key_features": {
      "avg_ip_last_3": 5.1,
      "days_rest": 5
    },
    "result": "NO_ACTION",
    "actual_score": "pitcher stats not found",
    "created_at": "2026-04-20T10:30:19.782690",
    "settled_at": "2026-04-21T09:00:06.175045"
  },
  {
    "id": 77,
    "date": "2026-04-20",
    "model": "f5_under",
    "game": "Athletics @ Seattle Mariners",
    "play": "F5 Under 4.7",
    "edge_pct": 46.1,
    "our_prob": 76.6,
    "market_prob": 52.4,
    "best_odds": -102,
    "best_book": "BetMGM",
    "key_features": {
      "away_pitcher_era_l5": 2.98,
      "home_pitcher_era_l5": 1.26,
      "park_factor": 0.93
    },
    "result": "W",
    "actual_score": "1-3",
    "created_at": "2026-04-20T10:30:19.777402",
    "settled_at": "2026-04-21T09:00:06.170985"
  },
  {
    "id": 76,
    "date": "2026-04-19",
    "model": "ip_props",
    "game": "Los Angeles Dodgers @ Colorado Rockies",
    "play": "Michael Lorenzen Under 17.5 Outs",
    "edge_pct": 31.4,
    "our_prob": 12.0,
    "market_prob": 17.5,
    "best_odds": -102,
    "best_book": "FanDuel",
    "key_features": {
      "avg_ip_last_3": 2.8,
      "days_rest": 5
    },
    "result": "NO_ACTION",
    "actual_score": "pitcher stats not found",
    "created_at": "2026-04-19T10:30:30.151489",
    "settled_at": "2026-04-20T09:00:07.725271"
  },
  {
    "id": 75,
    "date": "2026-04-19",
    "model": "f5_under",
    "game": "Baltimore Orioles @ Cleveland Guardians",
    "play": "F5 Under 4.7",
    "edge_pct": 40.0,
    "our_prob": 73.3,
    "market_prob": 52.4,
    "best_odds": 108,
    "best_book": "Pinnacle",
    "key_features": {
      "away_pitcher_era_l5": 1.58,
      "home_pitcher_era_l5": 3.24,
      "park_factor": 0.97
    },
    "result": "L",
    "actual_score": "4-6",
    "created_at": "2026-04-19T10:30:30.149494",
    "settled_at": "2026-04-20T09:00:07.721623"
  },
  {
    "id": 74,
    "date": "2026-04-19",
    "model": "f5_under",
    "game": "Texas Rangers @ Seattle Mariners",
    "play": "F5 Under 4.7",
    "edge_pct": 42.0,
    "our_prob": 74.4,
    "market_prob": 52.4,
    "best_odds": -106,
    "best_book": "Pinnacle",
    "key_features": {
      "away_pitcher_era_l5": 3.28,
      "home_pitcher_era_l5": 2.01,
      "park_factor": 0.93
    },
    "result": "L",
    "actual_score": "0-5",
    "created_at": "2026-04-19T10:30:30.146904",
    "settled_at": "2026-04-20T09:00:07.728621"
  },
  {
    "id": 73,
    "date": "2026-04-19",
    "model": "ip_props",
    "game": "San Francisco Giants @ Washington Nationals",
    "play": "PJ Poulin Under 17.5 Outs",
    "edge_pct": 42.9,
    "our_prob": 10.0,
    "market_prob": 17.5,
    "best_odds": 101,
    "best_book": "Pinnacle",
    "key_features": {
      "avg_ip_last_3": 0.7,
      "days_rest": 2
    },
    "result": "NO_ACTION",
    "actual_score": "pitcher stats not found",
    "created_at": "2026-04-19T10:30:30.144014",
    "settled_at": "2026-04-20T09:00:07.727524"
  },
  {
    "id": 72,
    "date": "2026-04-19",
    "model": "ip_props",
    "game": "New York Mets @ Chicago Cubs",
    "play": "Tobias Myers Under 17.5 Outs",
    "edge_pct": 65.7,
    "our_prob": 6.0,
    "market_prob": 17.5,
    "best_odds": -104,
    "best_book": "Pinnacle",
    "key_features": {
      "avg_ip_last_3": 2.3,
      "days_rest": 4
    },
    "result": "NO_ACTION",
    "actual_score": "pitcher stats not found",
    "created_at": "2026-04-19T10:30:30.139321",
    "settled_at": "2026-04-20T09:00:07.726471"
  },
  {
    "id": 71,
    "date": "2026-04-18",
    "model": "f5_under",
    "game": "Cincinnati Reds @ Minnesota Twins",
    "play": "F5 Under 4.9",
    "edge_pct": 30.3,
    "our_prob": 68.2,
    "market_prob": 52.4,
    "best_odds": 100,
    "best_book": "FanDuel",
    "key_features": {
      "away_pitcher_era_l5": 3.03,
      "home_pitcher_era_l5": 1.32,
      "park_factor": 0.98
    },
    "result": "L",
    "actual_score": "2-4",
    "created_at": "2026-04-18T10:30:30.575230",
    "settled_at": "2026-04-19T09:00:05.204216"
  },
  {
    "id": 70,
    "date": "2026-04-18",
    "model": "ip_props",
    "game": "Los Angeles Dodgers @ Colorado Rockies",
    "play": "Ryan Feltner Under 17.5 Outs",
    "edge_pct": 31.4,
    "our_prob": 12.0,
    "market_prob": 17.5,
    "best_odds": 103,
    "best_book": "Pinnacle",
    "key_features": {
      "avg_ip_last_3": 4.0,
      "days_rest": 7
    },
    "result": "NO_ACTION",
    "actual_score": "pitcher stats not found",
    "created_at": "2026-04-18T10:30:30.573332",
    "settled_at": "2026-04-19T09:00:05.210090"
  },
  {
    "id": 69,
    "date": "2026-04-18",
    "model": "f5_under",
    "game": "Kansas City Royals @ New York Yankees",
    "play": "F5 Under 4.6",
    "edge_pct": 32.8,
    "our_prob": 69.5,
    "market_prob": 52.4,
    "best_odds": -105,
    "best_book": "BetMGM",
    "key_features": {
      "away_pitcher_era_l5": 2.48,
      "home_pitcher_era_l5": 2.58,
      "park_factor": 1.01
    },
    "result": "L",
    "actual_score": "0-7",
    "created_at": "2026-04-18T10:30:30.570768",
    "settled_at": "2026-04-19T09:00:05.206954"
  },
  {
    "id": 68,
    "date": "2026-04-18",
    "model": "ip_props",
    "game": "Texas Rangers @ Seattle Mariners",
    "play": "George Kirby Over 17.5 Outs",
    "edge_pct": 48.6,
    "our_prob": 26.0,
    "market_prob": 17.5,
    "best_odds": 108,
    "best_book": "Pinnacle",
    "key_features": {
      "avg_ip_last_5": 6.8,
      "opp_k_rate": 0.251
    },
    "result": "NO_ACTION",
    "actual_score": "pitcher stats not found",
    "created_at": "2026-04-18T10:30:30.567992",
    "settled_at": "2026-04-19T09:00:05.211269"
  },
  {
    "id": 67,
    "date": "2026-04-18",
    "model": "f5_under",
    "game": "Atlanta Braves @ Philadelphia Phillies",
    "play": "F5 Under 5.5",
    "edge_pct": 51.9,
    "our_prob": 79.6,
    "market_prob": 52.4,
    "best_odds": -102,
    "best_book": "BetMGM",
    "key_features": {
      "away_pitcher_era_l5": 1.99,
      "home_pitcher_era_l5": 1.11,
      "park_factor": 1.02
    },
    "result": "W",
    "actual_score": "3-1",
    "created_at": "2026-04-18T10:30:30.563914",
    "settled_at": "2026-04-19T09:00:05.199778"
  },
  {
    "id": 66,
    "date": "2026-04-17",
    "model": "ip_props",
    "game": "Toronto Blue Jays @ Arizona Diamondbacks",
    "play": "Eric Lauer Under 17.5 Outs",
    "edge_pct": 25.7,
    "our_prob": 13.0,
    "market_prob": 17.5,
    "best_odds": 103,
    "best_book": "Pinnacle",
    "key_features": {
      "avg_ip_last_3": 4.1,
      "days_rest": 6
    },
    "result": "NO_ACTION",
    "actual_score": "pitcher stats not found",
    "created_at": "2026-04-17T10:30:27.442510",
    "settled_at": "2026-04-18T09:00:05.264173"
  },
  {
    "id": 65,
    "date": "2026-04-17",
    "model": "f5_under",
    "game": "Los Angeles Dodgers @ Colorado Rockies",
    "play": "F5 Under 5.7",
    "edge_pct": 30.4,
    "our_prob": 68.3,
    "market_prob": 52.4,
    "best_odds": 105,
    "best_book": "Pinnacle",
    "key_features": {
      "away_pitcher_era_l5": 3.33,
      "home_pitcher_era_l5": 1.93,
      "park_factor": 1.12
    },
    "result": "L",
    "actual_score": "7-1",
    "created_at": "2026-04-17T10:30:27.440344",
    "settled_at": "2026-04-18T09:00:05.259322"
  },
  {
    "id": 64,
    "date": "2026-04-17",
    "model": "f5_under",
    "game": "Chicago White Sox @ Athletics",
    "play": "F5 Under 4.2",
    "edge_pct": 35.4,
    "our_prob": 70.9,
    "market_prob": 52.4,
    "best_odds": 101,
    "best_book": "Pinnacle",
    "key_features": {
      "away_pitcher_era_l5": 3.45,
      "home_pitcher_era_l5": 2.67,
      "park_factor": 1.0
    },
    "result": "L",
    "actual_score": "5-1",
    "created_at": "2026-04-17T10:30:27.437577",
    "settled_at": "2026-04-18T09:00:05.254433"
  },
  {
    "id": 63,
    "date": "2026-04-17",
    "model": "f5_under",
    "game": "Tampa Bay Rays @ Pittsburgh Pirates",
    "play": "F5 Under 5.8",
    "edge_pct": 38.8,
    "our_prob": 72.7,
    "market_prob": 52.4,
    "best_odds": -110,
    "best_book": "Pinnacle",
    "key_features": {
      "away_pitcher_era_l5": 2.47,
      "home_pitcher_era_l5": 2.33,
      "park_factor": 0.97
    },
    "result": "W",
    "actual_score": "0-1",
    "created_at": "2026-04-17T10:30:27.434733",
    "settled_at": "2026-04-18T09:00:05.262188"
  },
  {
    "id": 62,
    "date": "2026-04-17",
    "model": "f5_under",
    "game": "Kansas City Royals @ New York Yankees",
    "play": "F5 Under 4.6",
    "edge_pct": 72.0,
    "our_prob": 90.1,
    "market_prob": 52.4,
    "best_odds": -102,
    "best_book": "FanDuel",
    "key_features": {
      "away_pitcher_era_l5": 0.37,
      "home_pitcher_era_l5": 1.03,
      "park_factor": 1.01
    },
    "result": "W",
    "actual_score": "0-2",
    "created_at": "2026-04-17T10:30:27.429870",
    "settled_at": "2026-04-18T09:00:05.257966"
  },
  {
    "id": 61,
    "date": "2026-04-16",
    "model": "f5_under",
    "game": "Washington Nationals @ Pittsburgh Pirates",
    "play": "F5 Under 6.0",
    "edge_pct": 45.2,
    "our_prob": 76.1,
    "market_prob": 52.4,
    "best_odds": 103,
    "best_book": "Pinnacle",
    "key_features": {
      "away_pitcher_era_l5": 2.69,
      "home_pitcher_era_l5": 2.46,
      "park_factor": 0.97
    },
    "result": "L",
    "actual_score": "4-4",
    "created_at": "2026-04-16T10:30:18.745170",
    "settled_at": "2026-04-17T09:00:06.939922"
  },
  {
    "id": 60,
    "date": "2026-04-16",
    "model": "ip_props",
    "game": "Colorado Rockies @ Houston Astros",
    "play": "Ryan Weiss Under 17.5 Outs",
    "edge_pct": 48.6,
    "our_prob": 9.0,
    "market_prob": 17.5,
    "best_odds": 100,
    "best_book": "BetMGM",
    "key_features": {
      "avg_ip_last_3": 2.4,
      "days_rest": 6
    },
    "result": "NO_ACTION",
    "actual_score": "pitcher stats not found",
    "created_at": "2026-04-16T10:30:18.742957",
    "settled_at": "2026-04-17T09:00:06.934970"
  },
  {
    "id": 59,
    "date": "2026-04-16",
    "model": "ip_props",
    "game": "Colorado Rockies @ Houston Astros",
    "play": "Juan Mejia Under 17.5 Outs",
    "edge_pct": 54.3,
    "our_prob": 8.0,
    "market_prob": 17.5,
    "best_odds": 100,
    "best_book": "BetMGM",
    "key_features": {
      "avg_ip_last_3": 0.7,
      "days_rest": 2
    },
    "result": "NO_ACTION",
    "actual_score": "pitcher stats not found",
    "created_at": "2026-04-16T10:30:18.740360",
    "settled_at": "2026-04-17T09:00:06.932495"
  },
  {
    "id": 58,
    "date": "2026-04-16",
    "model": "ip_props",
    "game": "Los Angeles Angels @ New York Yankees",
    "play": "Max Fried Over 17.5 Outs",
    "edge_pct": 54.3,
    "our_prob": 27.0,
    "market_prob": 17.5,
    "best_odds": -103,
    "best_book": "Pinnacle",
    "key_features": {
      "avg_ip_last_5": 6.8,
      "opp_k_rate": 0.252
    },
    "result": "NO_ACTION",
    "actual_score": "pitcher stats not found",
    "created_at": "2026-04-16T10:30:18.737544",
    "settled_at": "2026-04-17T09:00:06.936833"
  },
  {
    "id": 57,
    "date": "2026-04-16",
    "model": "ip_props",
    "game": "Tampa Bay Rays @ Chicago White Sox",
    "play": "Jordan Leasure Under 17.5 Outs",
    "edge_pct": 82.9,
    "our_prob": 3.0,
    "market_prob": 17.5,
    "best_odds": 100,
    "best_book": "FanDuel",
    "key_features": {
      "avg_ip_last_3": 1.0,
      "days_rest": 4
    },
    "result": "NO_ACTION",
    "actual_score": "pitcher stats not found",
    "created_at": "2026-04-16T10:30:18.732046",
    "settled_at": "2026-04-17T09:00:06.938490"
  },
  {
    "id": 56,
    "date": "2026-04-15",
    "model": "f5_under",
    "game": "Boston Red Sox @ Minnesota Twins",
    "play": "F5 Under 5.5",
    "edge_pct": 29.0,
    "our_prob": 67.6,
    "market_prob": 52.4,
    "best_odds": 100,
    "best_book": "Pinnacle",
    "key_features": {
      "away_pitcher_era_l5": 2.4,
      "home_pitcher_era_l5": 3.5,
      "park_factor": 0.98
    },
    "result": "L",
    "actual_score": "7-1",
    "created_at": "2026-04-15T10:30:27.917471",
    "settled_at": "2026-04-16T09:00:04.642885"
  },
  {
    "id": 55,
    "date": "2026-04-15",
    "model": "f5_under",
    "game": "Toronto Blue Jays @ Milwaukee Brewers",
    "play": "F5 Under 5.5",
    "edge_pct": 55.5,
    "our_prob": 81.5,
    "market_prob": 52.4,
    "best_odds": -104,
    "best_book": "Pinnacle",
    "key_features": {
      "away_pitcher_era_l5": 2.31,
      "home_pitcher_era_l5": 1.26,
      "park_factor": 0.97
    },
    "result": "W",
    "actual_score": "1-0",
    "created_at": "2026-04-15T10:30:27.915423",
    "settled_at": "2026-04-16T09:00:04.653538"
  },
  {
    "id": 54,
    "date": "2026-04-15",
    "model": "ip_props",
    "game": "Washington Nationals @ Pittsburgh Pirates",
    "play": "Mason Montgomery Under 17.5 Outs",
    "edge_pct": 60.0,
    "our_prob": 7.0,
    "market_prob": 17.5,
    "best_odds": 103,
    "best_book": "Pinnacle",
    "key_features": {
      "avg_ip_last_3": 0.7,
      "days_rest": 1
    },
    "result": "NO_ACTION",
    "actual_score": "pitcher stats not found",
    "created_at": "2026-04-15T10:30:27.912555",
    "settled_at": "2026-04-16T09:00:04.655389"
  },
  {
    "id": 53,
    "date": "2026-04-15",
    "model": "f5_under",
    "game": "New York Mets @ Los Angeles Dodgers",
    "play": "F5 Under 5.3",
    "edge_pct": 68.0,
    "our_prob": 88.0,
    "market_prob": 52.4,
    "best_odds": -115,
    "best_book": "FanDuel",
    "key_features": {
      "away_pitcher_era_l5": 2.03,
      "home_pitcher_era_l5": 0.0,
      "park_factor": 1.0
    },
    "result": "W",
    "actual_score": "1-2",
    "created_at": "2026-04-15T10:30:27.909860",
    "settled_at": "2026-04-16T09:00:04.648348"
  },
  {
    "id": 52,
    "date": "2026-04-15",
    "model": "f5_under",
    "game": "Seattle Mariners @ San Diego Padres",
    "play": "F5 Under 4.9",
    "edge_pct": 69.9,
    "our_prob": 89.0,
    "market_prob": 52.4,
    "best_odds": 100,
    "best_book": "Pinnacle",
    "key_features": {
      "away_pitcher_era_l5": 0.92,
      "home_pitcher_era_l5": 0.59,
      "park_factor": 0.95
    },
    "result": "L",
    "actual_score": "6-0",
    "created_at": "2026-04-15T10:30:27.905638",
    "settled_at": "2026-04-16T09:00:04.650798"
  },
  {
    "id": 51,
    "date": "2026-04-14",
    "model": "f5_under",
    "game": "Texas Rangers @ Athletics",
    "play": "F5 Under 4.7",
    "edge_pct": 38.7,
    "our_prob": 72.7,
    "market_prob": 52.4,
    "best_odds": 102,
    "best_book": "Pinnacle",
    "key_features": {
      "away_pitcher_era_l5": 3.37,
      "home_pitcher_era_l5": 2.41,
      "park_factor": 1.0
    },
    "result": "W",
    "actual_score": "1-2",
    "created_at": "2026-04-14T10:30:28.189193",
    "settled_at": "2026-04-15T09:00:05.701245"
  },
  {
    "id": 50,
    "date": "2026-04-14",
    "model": "f5_under",
    "game": "Cleveland Guardians @ St. Louis Cardinals",
    "play": "F5 Under 4.8",
    "edge_pct": 42.0,
    "our_prob": 74.4,
    "market_prob": 52.4,
    "best_odds": -104,
    "best_book": "Pinnacle",
    "key_features": {
      "away_pitcher_era_l5": 3.45,
      "home_pitcher_era_l5": 1.56,
      "park_factor": 0.98
    },
    "result": "W",
    "actual_score": "2-2",
    "created_at": "2026-04-14T10:30:28.186872",
    "settled_at": "2026-04-15T09:00:05.695132"
  },
  {
    "id": 49,
    "date": "2026-04-14",
    "model": "f5_under",
    "game": "Toronto Blue Jays @ Milwaukee Brewers",
    "play": "F5 Under 5.3",
    "edge_pct": 48.1,
    "our_prob": 77.6,
    "market_prob": 52.4,
    "best_odds": 101,
    "best_book": "Pinnacle",
    "key_features": {
      "away_pitcher_era_l5": 1.44,
      "home_pitcher_era_l5": 2.52,
      "park_factor": 0.97
    },
    "result": "W",
    "actual_score": "1-3",
    "created_at": "2026-04-14T10:30:28.183697",
    "settled_at": "2026-04-15T09:00:05.703563"
  },
  {
    "id": 48,
    "date": "2026-04-14",
    "model": "ip_props",
    "game": "Chicago Cubs @ Philadelphia Phillies",
    "play": "Riley Martin Under 17.5 Outs",
    "edge_pct": 48.6,
    "our_prob": 9.0,
    "market_prob": 17.5,
    "best_odds": 101,
    "best_book": "Pinnacle",
    "key_features": {
      "avg_ip_last_3": 1.0,
      "days_rest": 2
    },
    "result": "NO_ACTION",
    "actual_score": "pitcher stats not found",
    "created_at": "2026-04-14T10:30:28.180157",
    "settled_at": "2026-04-15T09:00:05.692650"
  },
  {
    "id": 47,
    "date": "2026-04-14",
    "model": "f5_under",
    "game": "Seattle Mariners @ San Diego Padres",
    "play": "F5 Under 5.0",
    "edge_pct": 49.0,
    "our_prob": 78.1,
    "market_prob": 52.4,
    "best_odds": 103,
    "best_book": "Pinnacle",
    "key_features": {
      "away_pitcher_era_l5": 1.96,
      "home_pitcher_era_l5": 2.21,
      "park_factor": 0.95
    },
    "result": "W",
    "actual_score": "1-3",
    "created_at": "2026-04-14T10:30:28.174283",
    "settled_at": "2026-04-15T09:00:05.698399"
  },
  {
    "id": 46,
    "date": "2026-04-13",
    "model": "k_props",
    "game": "Los Angeles Angels @ New York Yankees",
    "play": "Yusei Kikuchi Over 5.2 Ks",
    "edge_pct": 10.2,
    "our_prob": 5.7,
    "market_prob": 5.2,
    "best_odds": 100,
    "best_book": "FanDuel",
    "key_features": {
      "k_per_9": 9.8,
      "opp_k_rate": 0.261,
      "recent_k_avg": 5.3
    },
    "result": "NO_ACTION",
    "actual_score": "pitcher stats not found",
    "created_at": "2026-04-13T10:30:22.986783",
    "settled_at": "2026-04-14T09:00:05.509097"
  },
  {
    "id": 45,
    "date": "2026-04-13",
    "model": "k_props",
    "game": "Los Angeles Angels @ New York Yankees",
    "play": "Will Warren Over 4.4 Ks",
    "edge_pct": 11.0,
    "our_prob": 4.9,
    "market_prob": 4.4,
    "best_odds": 100,
    "best_book": "FanDuel",
    "key_features": {
      "k_per_9": 8.6,
      "opp_k_rate": 0.257,
      "recent_k_avg": 4.7
    },
    "result": "NO_ACTION",
    "actual_score": "pitcher stats not found",
    "created_at": "2026-04-13T10:30:22.984556",
    "settled_at": "2026-04-14T09:00:05.507551"
  },
  {
    "id": 44,
    "date": "2026-04-13",
    "model": "k_props",
    "game": "Houston Astros @ Seattle Mariners",
    "play": "Mike Burrows Over 4.9 Ks",
    "edge_pct": 11.1,
    "our_prob": 5.4,
    "market_prob": 4.9,
    "best_odds": -105,
    "best_book": "Pinnacle",
    "key_features": {
      "k_per_9": 8.4,
      "opp_k_rate": 0.261,
      "recent_k_avg": 5.0
    },
    "result": "NO_ACTION",
    "actual_score": "pitcher stats not found",
    "created_at": "2026-04-13T10:30:22.981532",
    "settled_at": "2026-04-14T09:00:05.505879"
  },
  {
    "id": 43,
    "date": "2026-04-13",
    "model": "k_props",
    "game": "Texas Rangers @ Athletics",
    "play": "Nathan Eovaldi Over 6.1 Ks",
    "edge_pct": 12.4,
    "our_prob": 6.9,
    "market_prob": 6.1,
    "best_odds": -102,
    "best_book": "BetMGM",
    "key_features": {
      "k_per_9": 11.7,
      "opp_k_rate": 0.274,
      "recent_k_avg": 6.3
    },
    "result": "NO_ACTION",
    "actual_score": "pitcher stats not found",
    "created_at": "2026-04-13T10:30:22.978277",
    "settled_at": "2026-04-14T09:00:05.510435"
  },
  {
    "id": 42,
    "date": "2026-04-13",
    "model": "f5_under",
    "game": "Cleveland Guardians @ St. Louis Cardinals",
    "play": "F5 Under 4.7",
    "edge_pct": 36.4,
    "our_prob": 71.5,
    "market_prob": 52.4,
    "best_odds": -105,
    "best_book": "FanDuel",
    "key_features": {
      "away_pitcher_era_l5": 3.23,
      "home_pitcher_era_l5": 2.27,
      "park_factor": 0.98
    },
    "result": "L",
    "actual_score": "4-1",
    "created_at": "2026-04-13T10:30:22.972356",
    "settled_at": "2026-04-14T09:00:05.500569"
  },
  {
    "id": 41,
    "date": "2026-04-12",
    "model": "f5_under",
    "game": "Chicago White Sox @ Kansas City Royals",
    "play": "F5 Under 3.6",
    "edge_pct": 52.3,
    "our_prob": 79.8,
    "market_prob": 52.4,
    "best_odds": -112,
    "best_book": "Pinnacle",
    "key_features": {
      "away_pitcher_era_l5": 2.59,
      "home_pitcher_era_l5": 1.75,
      "park_factor": 0.98
    },
    "result": "L",
    "actual_score": "4-5",
    "created_at": "2026-04-12T10:30:31.510154",
    "settled_at": "2026-04-13T09:00:05.708122"
  },
  {
    "id": 40,
    "date": "2026-04-12",
    "model": "f5_under",
    "game": "Los Angeles Angels @ Cincinnati Reds",
    "play": "F5 Under 4.3",
    "edge_pct": 58.3,
    "our_prob": 82.9,
    "market_prob": 52.4,
    "best_odds": -108,
    "best_book": "DraftKings",
    "key_features": {
      "away_pitcher_era_l5": 0.15,
      "home_pitcher_era_l5": 2.09,
      "park_factor": 1.03
    },
    "result": "L",
    "actual_score": "7-0",
    "created_at": "2026-04-12T10:30:31.507579",
    "settled_at": "2026-04-13T09:00:05.715094"
  },
  {
    "id": 39,
    "date": "2026-04-12",
    "model": "f5_under",
    "game": "New York Yankees @ Tampa Bay Rays",
    "play": "F5 Under 5.2",
    "edge_pct": 64.1,
    "our_prob": 86.0,
    "market_prob": 52.4,
    "best_odds": -101,
    "best_book": "Pinnacle",
    "key_features": {
      "away_pitcher_era_l5": 0.54,
      "home_pitcher_era_l5": 1.8,
      "park_factor": 0.96
    },
    "result": "W",
    "actual_score": "0-3",
    "created_at": "2026-04-12T10:30:31.504107",
    "settled_at": "2026-04-13T09:00:05.720268"
  },
  {
    "id": 38,
    "date": "2026-04-12",
    "model": "ip_props",
    "game": "Chicago White Sox @ Kansas City Royals",
    "play": "Grant Taylor Under 17.5 Outs",
    "edge_pct": 65.7,
    "our_prob": 6.0,
    "market_prob": 17.5,
    "best_odds": -102,
    "best_book": "FanDuel",
    "key_features": {
      "avg_ip_last_3": 1.0,
      "days_rest": 3
    },
    "result": "NO_ACTION",
    "actual_score": "pitcher stats not found",
    "created_at": "2026-04-12T10:30:31.500319",
    "settled_at": "2026-04-13T09:00:05.713515"
  },
  {
    "id": 37,
    "date": "2026-04-12",
    "model": "f5_under",
    "game": "Miami Marlins @ Detroit Tigers",
    "play": "F5 Under 5.0",
    "edge_pct": 69.8,
    "our_prob": 88.9,
    "market_prob": 52.4,
    "best_odds": -102,
    "best_book": "BetMGM",
    "key_features": {
      "away_pitcher_era_l5": 0.25,
      "home_pitcher_era_l5": 1.08,
      "park_factor": 0.96
    },
    "result": "W",
    "actual_score": "0-4",
    "created_at": "2026-04-12T10:30:31.494631",
    "settled_at": "2026-04-13T09:00:05.717716"
  },
  {
    "id": 36,
    "date": "2026-04-11",
    "model": "ip_props",
    "game": "San Francisco Giants @ Baltimore Orioles",
    "play": "Chris Bassitt Under 17.5 Outs",
    "edge_pct": 48.6,
    "our_prob": 9.0,
    "market_prob": 17.5,
    "best_odds": 102,
    "best_book": "Pinnacle",
    "key_features": {
      "avg_ip_last_3": 3.0,
      "days_rest": 6
    },
    "result": "NO_ACTION",
    "actual_score": "pitcher stats not found",
    "created_at": "2026-04-11T10:30:30.849131",
    "settled_at": "2026-04-12T09:00:05.561539"
  },
  {
    "id": 35,
    "date": "2026-04-11",
    "model": "f5_under",
    "game": "Houston Astros @ Seattle Mariners",
    "play": "F5 Under 5.6",
    "edge_pct": 49.0,
    "our_prob": 78.1,
    "market_prob": 52.4,
    "best_odds": -104,
    "best_book": "Pinnacle",
    "key_features": {
      "away_pitcher_era_l5": 2.28,
      "home_pitcher_era_l5": 1.4,
      "park_factor": 0.93
    },
    "result": "L",
    "actual_score": "7-7",
    "created_at": "2026-04-11T10:30:30.846786",
    "settled_at": "2026-04-12T09:00:05.554854"
  },
  {
    "id": 34,
    "date": "2026-04-11",
    "model": "f5_under",
    "game": "New York Yankees @ Tampa Bay Rays",
    "play": "F5 Under 5.2",
    "edge_pct": 59.3,
    "our_prob": 83.4,
    "market_prob": 52.4,
    "best_odds": -108,
    "best_book": "Pinnacle",
    "key_features": {
      "away_pitcher_era_l5": 0.45,
      "home_pitcher_era_l5": 2.62,
      "park_factor": 0.96
    },
    "result": "W",
    "actual_score": "1-1",
    "created_at": "2026-04-11T10:30:30.843873",
    "settled_at": "2026-04-12T09:00:05.557457"
  },
  {
    "id": 33,
    "date": "2026-04-11",
    "model": "f5_under",
    "game": "Cleveland Guardians @ Atlanta Braves",
    "play": "F5 Under 5.3",
    "edge_pct": 62.0,
    "our_prob": 84.9,
    "market_prob": 52.4,
    "best_odds": -105,
    "best_book": "DraftKings",
    "key_features": {
      "away_pitcher_era_l5": 0.41,
      "home_pitcher_era_l5": 1.93,
      "park_factor": 1.0
    },
    "result": "W",
    "actual_score": "1-0",
    "created_at": "2026-04-11T10:30:30.841217",
    "settled_at": "2026-04-12T09:00:05.550083"
  },
  {
    "id": 32,
    "date": "2026-04-11",
    "model": "f5_under",
    "game": "Pittsburgh Pirates @ Chicago Cubs",
    "play": "F5 Under 5.0",
    "edge_pct": 65.5,
    "our_prob": 86.7,
    "market_prob": 52.4,
    "best_odds": 100,
    "best_book": "BetMGM",
    "key_features": {
      "away_pitcher_era_l5": 2.62,
      "home_pitcher_era_l5": 0.0,
      "park_factor": 1.01
    },
    "result": "W",
    "actual_score": "3-1",
    "created_at": "2026-04-11T10:30:30.836516",
    "settled_at": "2026-04-12T09:00:05.559722"
  },
  {
    "id": 31,
    "date": "2026-04-10",
    "model": "k_props",
    "game": "Houston Astros @ Seattle Mariners",
    "play": "Tatsuya Imai Over 6.0 Ks",
    "edge_pct": 17.4,
    "our_prob": 7.0,
    "market_prob": 6.0,
    "best_odds": -105,
    "best_book": "DraftKings",
    "key_features": {
      "k_per_9": 14.0,
      "opp_k_rate": 0.276,
      "recent_k_avg": 6.5
    },
    "result": "NO_ACTION",
    "actual_score": "pitcher stats not found",
    "created_at": "2026-04-10T10:30:28.602418",
    "settled_at": "2026-04-11T09:00:05.523160"
  },
  {
    "id": 30,
    "date": "2026-04-10",
    "model": "ip_props",
    "game": "Boston Red Sox @ St. Louis Cardinals",
    "play": "Dustin May Under 17.5 Outs",
    "edge_pct": 20.0,
    "our_prob": 14.0,
    "market_prob": 17.5,
    "best_odds": -104,
    "best_book": "Pinnacle",
    "key_features": {
      "avg_ip_last_3": 3.5,
      "days_rest": 6
    },
    "result": "NO_ACTION",
    "actual_score": "pitcher stats not found",
    "created_at": "2026-04-10T10:30:28.600602",
    "settled_at": "2026-04-11T09:00:05.519975"
  },
  {
    "id": 29,
    "date": "2026-04-10",
    "model": "f5_under",
    "game": "Athletics @ New York Mets",
    "play": "F5 Under 4.8",
    "edge_pct": 32.5,
    "our_prob": 69.4,
    "market_prob": 52.4,
    "best_odds": 103,
    "best_book": "Pinnacle",
    "key_features": {
      "away_pitcher_era_l5": 2.77,
      "home_pitcher_era_l5": 2.3,
      "park_factor": 1.0
    },
    "result": "W",
    "actual_score": "1-0",
    "created_at": "2026-04-10T10:30:28.597821",
    "settled_at": "2026-04-11T09:00:05.513583"
  },
  {
    "id": 28,
    "date": "2026-04-10",
    "model": "ip_props",
    "game": "Colorado Rockies @ San Diego Padres",
    "play": "Walker Buehler Under 17.5 Outs",
    "edge_pct": 42.9,
    "our_prob": 10.0,
    "market_prob": 17.5,
    "best_odds": 100,
    "best_book": "Pinnacle",
    "key_features": {
      "avg_ip_last_3": 3.1,
      "days_rest": 5
    },
    "result": "NO_ACTION",
    "actual_score": "pitcher stats not found",
    "created_at": "2026-04-10T10:30:28.594866",
    "settled_at": "2026-04-11T09:00:05.521460"
  },
  {
    "id": 27,
    "date": "2026-04-10",
    "model": "ip_props",
    "game": "Athletics @ New York Mets",
    "play": "J.T. Ginn Under 17.5 Outs",
    "edge_pct": 54.3,
    "our_prob": 8.0,
    "market_prob": 17.5,
    "best_odds": 103,
    "best_book": "Pinnacle",
    "key_features": {
      "avg_ip_last_3": 2.1,
      "days_rest": 5
    },
    "result": "NO_ACTION",
    "actual_score": "pitcher stats not found",
    "created_at": "2026-04-10T10:30:28.589076",
    "settled_at": "2026-04-11T09:00:05.518418"
  },
  {
    "id": 26,
    "date": "2026-04-09",
    "model": "ip_props",
    "game": "Detroit Tigers @ Minnesota Twins",
    "play": "Mick Abel Under 17.5 Outs",
    "edge_pct": 14.3,
    "our_prob": 15.0,
    "market_prob": 17.5,
    "best_odds": 101,
    "best_book": "Pinnacle",
    "key_features": {
      "avg_ip_last_3": 3.5,
      "days_rest": 5
    },
    "result": "NO_ACTION",
    "actual_score": "pitcher stats not found",
    "created_at": "2026-04-09T10:30:11.573122",
    "settled_at": "2026-04-10T09:00:02.861944"
  },
  {
    "id": 25,
    "date": "2026-04-09",
    "model": "k_props",
    "game": "Athletics @ New York Yankees",
    "play": "Ryan Weathers Over 5.2 Ks",
    "edge_pct": 18.5,
    "our_prob": 6.2,
    "market_prob": 5.2,
    "best_odds": -105,
    "best_book": "BetMGM",
    "key_features": {
      "k_per_9": 12.4,
      "opp_k_rate": 0.293,
      "recent_k_avg": 5.5
    },
    "result": "NO_ACTION",
    "actual_score": "pitcher stats not found",
    "created_at": "2026-04-09T10:30:11.570335",
    "settled_at": "2026-04-10T09:00:02.857458"
  },
  {
    "id": 24,
    "date": "2026-04-09",
    "model": "f5_under",
    "game": "Athletics @ New York Yankees",
    "play": "F5 Under 5.3",
    "edge_pct": 25.6,
    "our_prob": 65.8,
    "market_prob": 52.4,
    "best_odds": -105,
    "best_book": "BetMGM",
    "key_features": {
      "away_pitcher_era_l5": 2.88,
      "home_pitcher_era_l5": 3.29,
      "park_factor": 1.01
    },
    "result": "W",
    "actual_score": "0-0",
    "created_at": "2026-04-09T10:30:11.566815",
    "settled_at": "2026-04-10T09:00:02.854306"
  },
  {
    "id": 23,
    "date": "2026-04-09",
    "model": "ip_props",
    "game": "Detroit Tigers @ Minnesota Twins",
    "play": "Jack Flaherty Under 17.5 Outs",
    "edge_pct": 31.4,
    "our_prob": 12.0,
    "market_prob": 17.5,
    "best_odds": 101,
    "best_book": "Pinnacle",
    "key_features": {
      "avg_ip_last_3": 4.0,
      "days_rest": 5
    },
    "result": "NO_ACTION",
    "actual_score": "pitcher stats not found",
    "created_at": "2026-04-09T10:30:11.562650",
    "settled_at": "2026-04-10T09:00:02.860290"
  },
  {
    "id": 22,
    "date": "2026-04-09",
    "model": "f5_under",
    "game": "Arizona Diamondbacks @ New York Mets",
    "play": "F5 Under 4.8",
    "edge_pct": 64.3,
    "our_prob": 86.1,
    "market_prob": 52.4,
    "best_odds": -105,
    "best_book": "BetMGM",
    "key_features": {
      "away_pitcher_era_l5": 0.0,
      "home_pitcher_era_l5": 3.1,
      "park_factor": 1.0
    },
    "result": "W",
    "actual_score": "0-1",
    "created_at": "2026-04-09T10:30:11.555748",
    "settled_at": "2026-04-10T09:00:02.848642"
  },
  {
    "id": 21,
    "date": "2026-04-08",
    "model": "ip_props",
    "game": "Athletics @ New York Yankees",
    "play": "Luis Severino Under 17.5 Outs",
    "edge_pct": 31.4,
    "our_prob": 12.0,
    "market_prob": 17.5,
    "best_odds": 100,
    "best_book": "Pinnacle",
    "key_features": {
      "avg_ip_last_3": 4.0,
      "days_rest": 7
    },
    "result": "NO_ACTION",
    "actual_score": "pitcher stats not found",
    "created_at": "2026-04-08T10:30:31.303486",
    "settled_at": "2026-04-09T09:00:04.719371"
  },
  {
    "id": 20,
    "date": "2026-04-08",
    "model": "ip_props",
    "game": "Seattle Mariners @ Texas Rangers",
    "play": "Bryan Woo Over 17.5 Outs",
    "edge_pct": 31.4,
    "our_prob": 23.0,
    "market_prob": 17.5,
    "best_odds": 100,
    "best_book": "FanDuel",
    "key_features": {
      "avg_ip_last_5": 6.5,
      "opp_k_rate": 0.253
    },
    "result": "NO_ACTION",
    "actual_score": "pitcher stats not found",
    "created_at": "2026-04-08T10:30:31.300493",
    "settled_at": "2026-04-09T09:00:04.727398"
  },
  {
    "id": 19,
    "date": "2026-04-08",
    "model": "f5_under",
    "game": "Seattle Mariners @ Texas Rangers",
    "play": "F5 Under 4.1",
    "edge_pct": 32.3,
    "our_prob": 69.3,
    "market_prob": 52.4,
    "best_odds": -103,
    "best_book": "Pinnacle",
    "key_features": {
      "away_pitcher_era_l5": 2.19,
      "home_pitcher_era_l5": 3.67,
      "park_factor": 1.04
    },
    "result": "W",
    "actual_score": "0-3",
    "created_at": "2026-04-08T10:30:31.297050",
    "settled_at": "2026-04-09T09:00:04.728919"
  },
  {
    "id": 18,
    "date": "2026-04-08",
    "model": "ip_props",
    "game": "Chicago Cubs @ Tampa Bay Rays",
    "play": "Colin Rea Under 17.5 Outs",
    "edge_pct": 48.6,
    "our_prob": 9.0,
    "market_prob": 17.5,
    "best_odds": -102,
    "best_book": "Pinnacle",
    "key_features": {
      "avg_ip_last_3": 3.0,
      "days_rest": 5
    },
    "result": "NO_ACTION",
    "actual_score": "pitcher stats not found",
    "created_at": "2026-04-08T10:30:31.292568",
    "settled_at": "2026-04-09T09:00:04.722864"
  },
  {
    "id": 17,
    "date": "2026-04-08",
    "model": "f5_under",
    "game": "San Diego Padres @ Pittsburgh Pirates",
    "play": "F5 Under 4.7",
    "edge_pct": 55.2,
    "our_prob": 81.3,
    "market_prob": 52.4,
    "best_odds": 105,
    "best_book": "Pinnacle",
    "key_features": {
      "away_pitcher_era_l5": 1.69,
      "home_pitcher_era_l5": 0.75,
      "park_factor": 0.97
    },
    "result": "W",
    "actual_score": "0-0",
    "created_at": "2026-04-08T10:30:31.287272",
    "settled_at": "2026-04-09T09:00:04.725000"
  },
  {
    "id": 16,
    "date": "2026-04-07",
    "model": "f5_under",
    "game": "Philadelphia Phillies @ San Francisco Giants",
    "play": "F5 Under 4.0",
    "edge_pct": 47.2,
    "our_prob": 77.1,
    "market_prob": 52.4,
    "best_odds": -105,
    "best_book": "Pinnacle",
    "key_features": {
      "away_pitcher_era_l5": 0.4,
      "home_pitcher_era_l5": 3.38,
      "park_factor": 0.95
    },
    "result": "W",
    "actual_score": "0-3",
    "created_at": "2026-04-07T10:30:28.298625",
    "settled_at": "2026-04-08T09:00:06.469820"
  },
  {
    "id": 15,
    "date": "2026-04-07",
    "model": "f5_under",
    "game": "Los Angeles Dodgers @ Toronto Blue Jays",
    "play": "F5 Under 6.0",
    "edge_pct": 57.2,
    "our_prob": 82.3,
    "market_prob": 52.4,
    "best_odds": -104,
    "best_book": "FanDuel",
    "key_features": {
      "away_pitcher_era_l5": 3.0,
      "home_pitcher_era_l5": 1.12,
      "park_factor": 0.99
    },
    "result": "W",
    "actual_score": "3-0",
    "created_at": "2026-04-07T10:30:28.294559",
    "settled_at": "2026-04-08T09:00:06.467592"
  },
  {
    "id": 14,
    "date": "2026-04-07",
    "model": "ip_props",
    "game": "Baltimore Orioles @ Chicago White Sox",
    "play": "Shane Smith Under 17.5 Outs",
    "edge_pct": 60.0,
    "our_prob": 7.0,
    "market_prob": 17.5,
    "best_odds": 103,
    "best_book": "Pinnacle",
    "key_features": {
      "avg_ip_last_3": 2.1,
      "days_rest": 6
    },
    "result": "NO_ACTION",
    "actual_score": "pitcher stats not found",
    "created_at": "2026-04-07T10:30:28.290988",
    "settled_at": "2026-04-08T09:00:06.459643"
  },
  {
    "id": 13,
    "date": "2026-04-07",
    "model": "f5_under",
    "game": "Cincinnati Reds @ Miami Marlins",
    "play": "F5 Under 4.5",
    "edge_pct": 64.6,
    "our_prob": 86.2,
    "market_prob": 52.4,
    "best_odds": 102,
    "best_book": "DraftKings",
    "key_features": {
      "away_pitcher_era_l5": 1.54,
      "home_pitcher_era_l5": 0.0,
      "park_factor": 0.94
    },
    "result": "W",
    "actual_score": "0-2",
    "created_at": "2026-04-07T10:30:28.287168",
    "settled_at": "2026-04-08T09:00:06.462067"
  },
  {
    "id": 12,
    "date": "2026-04-07",
    "model": "f5_under",
    "game": "Detroit Tigers @ Minnesota Twins",
    "play": "F5 Under 5.2",
    "edge_pct": 73.8,
    "our_prob": 91.1,
    "market_prob": 52.4,
    "best_odds": 104,
    "best_book": "Pinnacle",
    "key_features": {
      "away_pitcher_era_l5": 0.34,
      "home_pitcher_era_l5": 1.48,
      "park_factor": 0.98
    },
    "result": "W",
    "actual_score": "0-4",
    "created_at": "2026-04-07T10:30:28.279856",
    "settled_at": "2026-04-08T09:00:06.464730"
  },
  {
    "id": 11,
    "date": "2026-04-06",
    "model": "k_props",
    "game": "Atlanta Braves @ Los Angeles Angels",
    "play": "Chris Sale Over 4.5 Ks",
    "edge_pct": 12.7,
    "our_prob": 5.1,
    "market_prob": 4.5,
    "best_odds": 102,
    "best_book": "Pinnacle",
    "key_features": {
      "k_per_9": 6.8,
      "opp_k_rate": 0.285,
      "recent_k_avg": 4.5
    },
    "result": "NO_ACTION",
    "actual_score": "pitcher stats not found",
    "created_at": "2026-04-06T10:30:12.764928",
    "settled_at": "2026-04-07T09:00:04.328356"
  },
  {
    "id": 10,
    "date": "2026-04-06",
    "model": "k_props",
    "game": "Seattle Mariners @ Texas Rangers",
    "play": "Logan Gilbert Over 6.2 Ks",
    "edge_pct": 12.8,
    "our_prob": 7.0,
    "market_prob": 6.2,
    "best_odds": 103,
    "best_book": "Pinnacle",
    "key_features": {
      "k_per_9": 11.0,
      "opp_k_rate": 0.264,
      "recent_k_avg": 6.5
    },
    "result": "NO_ACTION",
    "actual_score": "pitcher stats not found",
    "created_at": "2026-04-06T10:30:12.761618",
    "settled_at": "2026-04-07T09:00:04.335407"
  },
  {
    "id": 9,
    "date": "2026-04-06",
    "model": "ip_props",
    "game": "Baltimore Orioles @ Chicago White Sox",
    "play": "Grant Taylor Under 17.5 Outs",
    "edge_pct": 65.7,
    "our_prob": 6.0,
    "market_prob": 17.5,
    "best_odds": 102,
    "best_book": "Pinnacle",
    "key_features": {
      "avg_ip_last_3": 1.0,
      "days_rest": 2
    },
    "result": "NO_ACTION",
    "actual_score": "pitcher stats not found",
    "created_at": "2026-04-06T10:30:12.758182",
    "settled_at": "2026-04-07T09:00:04.334361"
  },
  {
    "id": 8,
    "date": "2026-04-06",
    "model": "f5_under",
    "game": "Atlanta Braves @ Los Angeles Angels",
    "play": "F5 Under 5.2",
    "edge_pct": 86.1,
    "our_prob": 97.5,
    "market_prob": 52.4,
    "best_odds": 102,
    "best_book": "Pinnacle",
    "key_features": {
      "away_pitcher_era_l5": 0.38,
      "home_pitcher_era_l5": 0.0,
      "park_factor": 0.99
    },
    "result": "L",
    "actual_score": "1-6",
    "created_at": "2026-04-06T10:30:12.751640",
    "settled_at": "2026-04-07T09:00:04.331143"
  },
  {
    "id": 7,
    "date": "2026-04-04",
    "model": "ip_props",
    "game": "Toronto Blue Jays @ Chicago White Sox",
    "play": "Grant Taylor Under 17.5 Outs",
    "edge_pct": 48.6,
    "our_prob": 9.0,
    "market_prob": 17.5,
    "best_odds": 100,
    "best_book": "Pinnacle",
    "key_features": {
      "avg_ip_last_3": 1.0,
      "days_rest": 1
    },
    "result": "NO_ACTION",
    "actual_score": "pitcher stats not found",
    "created_at": "2026-04-04T10:30:15.670935",
    "settled_at": "2026-04-05T09:00:08.028861"
  },
  {
    "id": 6,
    "date": "2026-04-04",
    "model": "k_props",
    "game": "Toronto Blue Jays @ Chicago White Sox",
    "play": "Mason Fluharty Over 0.5 Ks",
    "edge_pct": 80.1,
    "our_prob": 0.8,
    "market_prob": 0.5,
    "best_odds": 100,
    "best_book": "Pinnacle",
    "key_features": {
      "k_per_9": 21.6,
      "opp_k_rate": 0.329,
      "recent_k_avg": 1.0
    },
    "result": "NO_ACTION",
    "actual_score": "pitcher stats not found",
    "created_at": "2026-04-04T10:30:15.667587",
    "settled_at": "2026-04-05T09:00:08.032463"
  },
  {
    "id": 5,
    "date": "2026-04-04",
    "model": "ip_props",
    "game": "Toronto Blue Jays @ Chicago White Sox",
    "play": "Mason Fluharty Under 17.5 Outs",
    "edge_pct": 88.6,
    "our_prob": 2.0,
    "market_prob": 17.5,
    "best_odds": 100,
    "best_book": "Pinnacle",
    "key_features": {
      "avg_ip_last_3": 0.2,
      "days_rest": 3
    },
    "result": "NO_ACTION",
    "actual_score": "pitcher stats not found",
    "created_at": "2026-04-04T10:30:15.661699",
    "settled_at": "2026-04-05T09:00:08.034125"
  },
  {
    "id": 4,
    "date": "2026-04-03",
    "model": "ip_props",
    "game": "Toronto Blue Jays @ Chicago White Sox",
    "play": "Grant Taylor Under 17.5 Outs",
    "edge_pct": 82.9,
    "our_prob": 3.0,
    "market_prob": 17.5,
    "best_odds": 100,
    "best_book": "DraftKings",
    "key_features": {
      "avg_ip_last_3": 1.0,
      "days_rest": 5
    },
    "result": "NO_ACTION",
    "actual_score": "pitcher stats not found",
    "created_at": "2026-04-03T10:30:11.992440",
    "settled_at": "2026-04-04T09:00:06.358217"
  },
  {
    "id": 3,
    "date": "2026-03-31",
    "model": "k_props",
    "game": "Washington Nationals @ Philadelphia Phillies",
    "play": "PJ Poulin Over 0.4 Ks",
    "edge_pct": 28.5,
    "our_prob": 0.5,
    "market_prob": 0.4,
    "best_odds": 102,
    "best_book": "Pinnacle",
    "key_features": {
      "k_per_9": 5.4,
      "opp_k_rate": 0.263,
      "recent_k_avg": 0.5
    },
    "result": "NO_ACTION",
    "actual_score": "pitcher stats not found",
    "created_at": "2026-03-31T10:30:14.368305",
    "settled_at": "2026-04-01T09:00:04.700731"
  },
  {
    "id": 2,
    "date": "2026-03-31",
    "model": "ip_props",
    "game": "Washington Nationals @ Philadelphia Phillies",
    "play": "PJ Poulin Under 17.5 Outs",
    "edge_pct": 71.4,
    "our_prob": 5.0,
    "market_prob": 17.5,
    "best_odds": 102,
    "best_book": "Pinnacle",
    "key_features": {
      "avg_ip_last_3": 0.6,
      "days_rest": 2
    },
    "result": "NO_ACTION",
    "actual_score": "pitcher stats not found",
    "created_at": "2026-03-31T10:30:14.361571",
    "settled_at": "2026-04-01T09:00:04.705273"
  }
]